[{"_id": "Любляна", "max_salary": "74813", "min_salary": 61090.05, "avg_salary": 101239.8642857143}, {"_id": "Севилья", "max_salary": "94656", "min_salary": 36409, "avg_salary": 99705.0}, {"_id": "Виго", "max_salary": "91048", "min_salary": 69701, "avg_salary": 106023.875}, {"_id": "Вальядолид", "max_salary": "96764", "min_salary": 30163, "avg_salary": 76538.25}, {"_id": "Ташкент", "max_salary": "81237", "min_salary": 42422, "avg_salary": 73235.83333333333}, {"_id": "Бланес", "max_salary": "94689", "min_salary": 132988, "avg_salary": 132988.0}, {"_id": "Санхенхо", "max_salary": "95646", "min_salary": 32974, "avg_salary": 72470.0}, {"_id": "Вроцлав", "max_salary": "191753", "min_salary": 114836, "avg_salary": 136043.75}, {"_id": "Алькала-де-Энарес", "max_salary": "94996", "min_salary": 32311, "avg_salary": 120872.0}, {"_id": "Сория", "max_salary": "94932", "min_salary": 26416, "avg_salary": 73980.12142857142}, {"_id": "Скопье", "max_salary": "88819", "min_salary": 30969, "avg_salary": 115365.0}, {"_id": "Санкт-Петербург", "max_salary": "46871", "min_salary": 35405, "avg_salary": 78357.4}, {"_id": "Белград", "max_salary": "82891", "min_salary": 34154, "avg_salary": 103192.96111111112}, {"_id": "Загреб", "max_salary": "193980", "min_salary": 50198, "avg_salary": 113580.88888888889}, {"_id": "Краков", "max_salary": "36026", "min_salary": 37136, "avg_salary": 87879.325}, {"_id": "Семана", "max_salary": "48427", "min_salary": 49064, "avg_salary": 108060.55}, {"_id": "Авилес", "max_salary": "91449", "min_salary": 71823, "avg_salary": 102513.875}, {"_id": "Рига", "max_salary": "92559", "min_salary": 32712, "avg_salary": 70552.0}, {"_id": "Валенсия", "max_salary": "98571", "min_salary": 29005, "avg_salary": 92506.08}, {"_id": "Вильнюс", "max_salary": "55108", "min_salary": 68429, "avg_salary": 94870.5}, {"_id": "Кишинев", "max_salary": "57774", "min_salary": 96072, "avg_salary": 135026.75}, {"_id": "Эльче", "max_salary": "78922", "min_salary": 36012, "avg_salary": 88221.32142857143}, {"_id": "Афины", "max_salary": "88678", "min_salary": 42342, "avg_salary": 79755.33333333333}, {"_id": "Аликанте", "max_salary": "86028", "min_salary": 34947.15, "avg_salary": 125847.17142857143}, {"_id": "Будапешт", "max_salary": "92297", "min_salary": 25505, "avg_salary": 72053.65714285713}, {"_id": "Прага", "max_salary": "37066", "min_salary": 32232.9, "avg_salary": 78038.225}, {"_id": "Сантьяго-де-Компостела", "max_salary": "85962", "min_salary": 65763, "avg_salary": 99410.85000000002}, {"_id": "Подгорица", "max_salary": "68255", "min_salary": 25706, "avg_salary": 75950.2}, {"_id": "Ереван", "max_salary": "94463", "min_salary": 25309, "avg_salary": 90520.75}, {"_id": "Тирана", "max_salary": "99642", "min_salary": 79513, "avg_salary": 112812.83333333333}, {"_id": "Монсон", "max_salary": "83510", "min_salary": 36546, "avg_salary": 86386.85555555555}, {"_id": "Мадрид", "max_salary": "29256", "min_salary": 35538, "avg_salary": 57106.0}, {"_id": "Осера", "max_salary": "55482", "min_salary": 35979, "avg_salary": 90821.88888888889}, {"_id": "Лас-Росас", "max_salary": "62168", "min_salary": 30376, "avg_salary": 89166.14285714286}, {"_id": "Минск", "max_salary": "57011", "min_salary": 39186, "avg_salary": 114797.59375}, {"_id": "Малага", "max_salary": "85470", "min_salary": 53656.05, "avg_salary": 91755.96428571429}, {"_id": "Луго", "max_salary": "58305", "min_salary": 32718, "avg_salary": 67448.33333333333}, {"_id": "Алма-Ата", "max_salary": "85253", "min_salary": 59521, "avg_salary": 93298.87142857142}, {"_id": "Навалькарнеро", "max_salary": "84815", "min_salary": 39201, "avg_salary": 97389.0}, {"_id": "Астана", "max_salary": "187685", "min_salary": 48663, "avg_salary": 105861.77777777778}, {"_id": "София", "max_salary": "81522", "min_salary": 29652, "avg_salary": 95109.36363636363}, {"_id": "Мерида", "max_salary": "70980", "min_salary": 42858, "avg_salary": 109329.3}, {"_id": "Тарраса", "max_salary": "74393", "min_salary": 37132, "avg_salary": 89101.33333333333}, {"_id": "Душанбе", "max_salary": "96497", "min_salary": 39533, "avg_salary": 79853.0}, {"_id": "Трухильо", "max_salary": "87939", "min_salary": 52795, "avg_salary": 105095.42857142857}, {"_id": "Барселона", "max_salary": "81224", "min_salary": 33683, "avg_salary": 78324.0}, {"_id": "Тбилиси", "max_salary": "96257", "min_salary": 39766.55, "avg_salary": 123922.39775}, {"_id": "Таллин", "max_salary": "79218", "min_salary": 32773, "avg_salary": 72231.14285714286}, {"_id": "Варшава", "max_salary": "89003", "min_salary": 69549, "avg_salary": 70565.0}, {"_id": "Бургос", "max_salary": "97805", "min_salary": 26449, "avg_salary": 98673.66666666667}, {"_id": "Гранада", "max_salary": "86051", "min_salary": 46436, "avg_salary": 101968.83333333333}, {"_id": "Самора", "max_salary": "75420", "min_salary": 58871, "avg_salary": 133375.38}, {"_id": "Сьюдад-Реаль", "max_salary": "75629", "min_salary": 39170, "avg_salary": 101016.28571428571}, {"_id": "Кордова", "max_salary": "57609", "min_salary": 34129, "avg_salary": 79933.95625}, {"_id": "Эль-Пуэрто-де-Санта-Мария", "max_salary": "95423", "min_salary": 103716, "avg_salary": 141144.325}, {"_id": "Сан-Себастьян", "max_salary": "65344", "min_salary": 43670, "avg_salary": 110020.4}, {"_id": "Овьедо", "max_salary": "95023", "min_salary": 27530, "avg_salary": 105621.73333333334}, {"_id": "Бишкек", "max_salary": "81896", "min_salary": 37556, "avg_salary": 70447.78571428571}, {"_id": "Кадакес", "max_salary": "89264", "min_salary": 37890, "avg_salary": 90756.125}, {"_id": "Ла-Корунья", "max_salary": "49799", "min_salary": 26227, "avg_salary": 95028.5}, {"_id": "Мартоса", "max_salary": "95878", "min_salary": 45305, "avg_salary": 86461.85714285714}, {"_id": "Бильбао", "max_salary": "32739", "min_salary": 29782, "avg_salary": 86758.44444444444}, {"_id": "Пласенсия", "max_salary": "99734", "min_salary": 61852, "avg_salary": 99396.28571428571}, {"_id": "Артейхо", "max_salary": "94386", "min_salary": 70735, "avg_salary": 122383.0}, {"_id": "Камбадос", "max_salary": "83485", "min_salary": 45186, "avg_salary": 88740.1}, {"_id": "Вильявисиоса", "max_salary": "67013", "min_salary": 30671.550000000003, "avg_salary": 109968.55833333333}, {"_id": "Махадаонда", "max_salary": "71202", "min_salary": 40216.05, "avg_salary": 109191.89444444445}, {"_id": "Куэнка", "max_salary": "60682", "min_salary": 29722, "avg_salary": 110076.125}, {"_id": "Тудела", "max_salary": "93618", "min_salary": 29142, "avg_salary": 111312.51428571428}, {"_id": "Луарка", "max_salary": "92431", "min_salary": 54032, "avg_salary": 84502.1}, {"_id": "Мурсия", "max_salary": "78767", "min_salary": 59753, "avg_salary": 107047.6}, {"_id": "Фигерас", "max_salary": "36917", "min_salary": 27612, "avg_salary": 116850.55555555556}, {"_id": "Сараево", "max_salary": "93260", "min_salary": 29132, "avg_salary": 69617.57142857143}, {"_id": "Льейда", "max_salary": "82638", "min_salary": 30805, "avg_salary": 89511.02727272728}, {"_id": "Хельсинки", "max_salary": "95466", "min_salary": 29949, "avg_salary": 95227.5}, {"_id": "Касерес", "max_salary": "24016", "min_salary": 35853, "avg_salary": 108977.66666666667}, {"_id": "Москва", "max_salary": "90724", "min_salary": 62437.200000000004, "avg_salary": 125481.92}, {"_id": "Баку", "max_salary": "96164", "min_salary": 26802, "avg_salary": 106249.5}, {"_id": "Сеговия", "max_salary": "68202", "min_salary": "168607", "avg_salary": null}, {"_id": "Хихон", "max_salary": "95232", "min_salary": 60798, "avg_salary": 119738.00555555556}, {"_id": "Картахена", "max_salary": "94754", "min_salary": 81182, "avg_salary": 125402.6}]